{
 "updated_iso": "2026-07-22",
 "updated_hi": "22 जुलाई 2026 को अपडेट",
 "updated_en": "Updated 22 July 2026",
 "usd_inr": 96.56,
 "mode": "live (per-ticker fallback on misses)",
 "india": {
  "Mukesh Ambani & family": {
   "lcr": 8.73,
   "usd": 90.4
  },
  "Gautam Adani & family": {
   "lcr": 12.43,
   "usd": 128.8
  },
  "Sunil Mittal & family": {
   "lcr": 2.8,
   "usd": 29.0
  },
  "Dilip Shanghvi & family": {
   "lcr": 2.54,
   "usd": 26.3
  },
  "RK Damani & family": {
   "lcr": 1.94,
   "usd": 20.1
  },
  "Shiv Nadar family": {
   "lcr": 2.04,
   "usd": 21.1
  },
  "Uday Kotak": {
   "lcr": 0.98,
   "usd": 10.2
  },
  "Ravi Jaipuria": {
   "lcr": 0.92,
   "usd": 9.5
  },
  "KP Singh & family": {
   "lcr": 1.19,
   "usd": 12.4
  },
  "Pankaj Patel & family": {
   "lcr": 0.84,
   "usd": 8.7
  },
  "Falguni Nayar & family": {
   "lcr": 0.49,
   "usd": 5.0
  }
 },
 "world": {
  "Elon Musk": {
   "usd": 868.7
  },
  "Mark Zuckerberg": {
   "usd": 215.4
  },
  "Jeff Bezos": {
   "usd": 230.8
  },
  "Jensen Huang": {
   "usd": 181.1
  },
  "Larry Ellison": {
   "usd": 149.0
  },
  "Bernard Arnault": {
   "usd": 133.4
  },
  "Mukesh Ambani": {
   "usd": 90.4
  },
  "Gautam Adani": {
   "usd": 128.8
  }
 }
}